subscriptions/__init__.py
subscriptions/__version__.py
subscriptions/decorators.py
subscriptions/exceptions.py
subscriptions/tests.py
subscriptions/types.py
stripe_subscriptions-0.5.3.dist-info/LICENSE.txt
stripe_subscriptions-0.5.3.dist-info/METADATA
stripe_subscriptions-0.5.3.dist-info/WHEEL
stripe_subscriptions-0.5.3.dist-info/top_level.txt
stripe_subscriptions-0.5.3.dist-info/RECORD
