Metadata-Version: 2.1
Name: stripe-subscriptions
Version: 0.5.3
Summary: Easier management of subscriptions with Stripe
Home-page: https://github.com/primal100/stripe-subscriptions
Author: Paul Martin
License: UNKNOWN
Platform: UNKNOWN
Classifier: Development Status :: 4 - Beta
Classifier: Programming Language :: Python :: 3
Classifier: Programming Language :: Python :: 3.6
Classifier: Programming Language :: Python :: 3.7
Classifier: Programming Language :: Python :: 3.8
Classifier: Programming Language :: Python :: 3.9
Classifier: License :: OSI Approved :: MIT License
Classifier: Operating System :: OS Independent
License-File: LICENSE.txt
Requires-Dist: stripe
Requires-Dist: typing-extensions (>=3.10.0.0) ; python_version < "3.8"
